UploadDownloadFilesCSC440/__init__.py
UploadDownloadFilesCSC440/download.py
UploadDownloadFilesCSC440/upload.py
UploadDownloadFilesCSC440-1.1.dist-info/METADATA
UploadDownloadFilesCSC440-1.1.dist-info/WHEEL
UploadDownloadFilesCSC440-1.1.dist-info/top_level.txt
UploadDownloadFilesCSC440-1.1.dist-info/RECORD
