Metadata-Version: 2.1
Name: UploadDownloadFilesCSC440
Version: 1.1
Summary: Uploading and downloading files using a Flask wiki app.
Home-page: UNKNOWN
Author: Rachel Robertson
Author-email: robertsona5@nku.edu
License: UNKNOWN
Platform: UNKNOWN
